{
    "name": "Khill\\Lavacharts\\Configs\\BoxStyle",
    "line": 23,
    "short_desc": "BoxStyle Object",
    "long_desc": "For charts that support annotations, the boxStyle object controls the appearance\nof the boxes surrounding annotations",
    "hint": null,
    "tags": {
        "package": [
            [
                "Lavacharts"
            ]
        ],
        "subpackage": [
            [
                "Configs"
            ]
        ],
        "author": [
            [
                "Kevin",
                "Hill",
                "<kevinkhill@gmail.com>"
            ]
        ],
        "copyright": [
            [
                "(c)",
                "2015,",
                "KHill",
                "Designs"
            ]
        ],
        "link": [
            [
                "http:\/\/github.com\/kevinkhill\/lavacharts",
                "GitHub",
                "Repository",
                "Page"
            ],
            [
                "http:\/\/lavacharts.com",
                "",
                "",
                "",
                "",
                "",
                "",
                "",
                "",
                "",
                "",
                "",
                "",
                "",
                "",
                "",
                "",
                "",
                "",
                "Official",
                "Docs",
                "Site"
            ]
        ],
        "license": [
            [
                "http:\/\/opensource.org\/licenses\/MIT",
                "MIT"
            ]
        ]
    },
    "namespace": "Khill\\Lavacharts\\Configs",
    "file": "\/home\/kevin\/projects\/php\/lavacharts-api\/..\/lavacharts\/src\/Configs\/BoxStyle.php",
    "relative_file": null,
    "hash": "3cde86361954ec652199ee59b24febf58b7aedf8",
    "parent": "Khill\\Lavacharts\\Configs\\ConfigObject",
    "modifiers": "Stmt_Class",
    "is_trait": false,
    "is_interface": false,
    "aliases": {
        "InvalidConfigValue": "Khill\\Lavacharts\\Exceptions\\InvalidConfigValue"
    },
    "errors": [],
    "interfaces": [],
    "traits": [],
    "properties": {
        "stroke": {
            "name": "stroke",
            "line": 30,
            "short_desc": "Color of the box outline.",
            "long_desc": "",
            "hint": [
                [
                    "string",
                    false
                ]
            ],
            "hint_desc": "",
            "tags": [],
            "modifiers": 1,
            "default": null,
            "errors": []
        },
        "strokeWidth": {
            "name": "strokeWidth",
            "line": 37,
            "short_desc": "Thickness of the box outline.",
            "long_desc": "",
            "hint": [
                [
                    "int",
                    false
                ],
                [
                    "string",
                    false
                ]
            ],
            "hint_desc": "",
            "tags": [],
            "modifiers": 1,
            "default": null,
            "errors": []
        },
        "rx": {
            "name": "rx",
            "line": 44,
            "short_desc": "X radius of the corner curvature.",
            "long_desc": "",
            "hint": [
                [
                    "int",
                    false
                ],
                [
                    "string",
                    false
                ]
            ],
            "hint_desc": "",
            "tags": [],
            "modifiers": 1,
            "default": null,
            "errors": []
        },
        "ry": {
            "name": "ry",
            "line": 51,
            "short_desc": "Y radius of the corner curvature.",
            "long_desc": "",
            "hint": [
                [
                    "int",
                    false
                ],
                [
                    "string",
                    false
                ]
            ],
            "hint_desc": "",
            "tags": [],
            "modifiers": 1,
            "default": null,
            "errors": []
        },
        "gradient": {
            "name": "gradient",
            "line": 58,
            "short_desc": "Attributes for linear gradient fill.",
            "long_desc": "",
            "hint": [
                [
                    "\\Khill\\Lavacharts\\Configs\\Gradient",
                    false
                ]
            ],
            "hint_desc": "",
            "tags": [],
            "modifiers": 1,
            "default": null,
            "errors": []
        }
    },
    "methods": {
        "__construct": {
            "name": "__construct",
            "line": 69,
            "short_desc": "Builds the Options object.",
            "long_desc": "Passing an array of key value pairs will set the configuration for each\nchild object created from this parent object.",
            "hint": [
                [
                    "Khill\\Lavacharts\\Configs\\BoxStyle",
                    false
                ]
            ],
            "hint_desc": "",
            "tags": [],
            "modifiers": "1",
            "is_by_ref": "",
            "exceptions": [
                [
                    "\\Khill\\Lavacharts\\Exceptions\\InvalidConfigValue",
                    ""
                ],
                [
                    "\\Khill\\Lavacharts\\Exceptions\\InvalidConfigProperty",
                    ""
                ]
            ],
            "errors": [],
            "parameters": {
                "config": {
                    "name": "config",
                    "line": 69,
                    "short_desc": "Array of options.",
                    "long_desc": null,
                    "hint": [
                        [
                            "array",
                            false
                        ]
                    ],
                    "tags": [],
                    "modifiers": "",
                    "default": "array()",
                    "is_by_ref": false
                }
            }
        },
        "stroke": {
            "name": "stroke",
            "line": 81,
            "short_desc": "If present, specifies the color for the box outline.",
            "long_desc": "If undefined, a random color will be used.",
            "hint": [
                [
                    "Khill\\Lavacharts\\Configs\\BoxStyle",
                    false
                ]
            ],
            "hint_desc": "",
            "tags": [],
            "modifiers": "1",
            "is_by_ref": "",
            "exceptions": [],
            "errors": [],
            "parameters": {
                "stroke": {
                    "name": "stroke",
                    "line": 81,
                    "short_desc": "Valid HTML color.",
                    "long_desc": null,
                    "hint": [
                        [
                            "string",
                            false
                        ]
                    ],
                    "tags": [],
                    "modifiers": "",
                    "default": null,
                    "is_by_ref": false
                }
            }
        },
        "strokeWidth": {
            "name": "strokeWidth",
            "line": 101,
            "short_desc": "Sets the thickness of the box outline.",
            "long_desc": "",
            "hint": [
                [
                    "Khill\\Lavacharts\\Configs\\BoxStyle",
                    false
                ]
            ],
            "hint_desc": "",
            "tags": [],
            "modifiers": "1",
            "is_by_ref": "",
            "exceptions": [],
            "errors": [],
            "parameters": {
                "strokeWidth": {
                    "name": "strokeWidth",
                    "line": 101,
                    "short_desc": "",
                    "long_desc": null,
                    "hint": [
                        [
                            "integer",
                            false
                        ],
                        [
                            "string",
                            false
                        ]
                    ],
                    "tags": [],
                    "modifiers": "",
                    "default": null,
                    "is_by_ref": false
                }
            }
        },
        "rx": {
            "name": "rx",
            "line": 121,
            "short_desc": "Sets the x-radius of the corner curvature.",
            "long_desc": "",
            "hint": [
                [
                    "Khill\\Lavacharts\\Configs\\BoxStyle",
                    false
                ]
            ],
            "hint_desc": "",
            "tags": [],
            "modifiers": "1",
            "is_by_ref": "",
            "exceptions": [],
            "errors": [],
            "parameters": {
                "rx": {
                    "name": "rx",
                    "line": 121,
                    "short_desc": "",
                    "long_desc": null,
                    "hint": [
                        [
                            "integer",
                            false
                        ],
                        [
                            "string",
                            false
                        ]
                    ],
                    "tags": [],
                    "modifiers": "",
                    "default": null,
                    "is_by_ref": false
                }
            }
        },
        "ry": {
            "name": "ry",
            "line": 141,
            "short_desc": "Sets the y-radius of the corner curvature.",
            "long_desc": "",
            "hint": [
                [
                    "Khill\\Lavacharts\\Configs\\BoxStyle",
                    false
                ]
            ],
            "hint_desc": "",
            "tags": [],
            "modifiers": "1",
            "is_by_ref": "",
            "exceptions": [],
            "errors": [],
            "parameters": {
                "ry": {
                    "name": "ry",
                    "line": 141,
                    "short_desc": "",
                    "long_desc": null,
                    "hint": [
                        [
                            "integer",
                            false
                        ],
                        [
                            "string",
                            false
                        ]
                    ],
                    "tags": [],
                    "modifiers": "",
                    "default": null,
                    "is_by_ref": false
                }
            }
        },
        "gradient": {
            "name": "gradient",
            "line": 161,
            "short_desc": "Sets the attributes for linear gradient fill.",
            "long_desc": "",
            "hint": [
                [
                    "Khill\\Lavacharts\\Configs\\BoxStyle",
                    false
                ]
            ],
            "hint_desc": "",
            "tags": [],
            "modifiers": "1",
            "is_by_ref": "",
            "exceptions": [],
            "errors": [],
            "parameters": {
                "gradient": {
                    "name": "gradient",
                    "line": 161,
                    "short_desc": "",
                    "long_desc": null,
                    "hint": [
                        [
                            "Khill\\Lavacharts\\Configs\\Khill\\Lavacharts\\Configs\\Gradient",
                            false
                        ]
                    ],
                    "tags": [],
                    "modifiers": "Khill\\Lavacharts\\Configs\\Gradient",
                    "default": null,
                    "is_by_ref": false
                }
            }
        }
    },
    "constants": []
}